qucat/__init__.py
qucat/_constants.py
qucat/_generate_graphics.py
qucat/_gui.py
qucat/_utility.py
qucat/core.py
qucat/plotting_settings.py
qucat/.graphics/C.jpg
qucat/.graphics/C.png
qucat/.graphics/C_hover.jpg
qucat/.graphics/C_hover.png
qucat/.graphics/C_hover_selected.jpg
qucat/.graphics/C_hover_selected.png
qucat/.graphics/C_selected.jpg
qucat/.graphics/C_selected.png
qucat/.graphics/G.jpg
qucat/.graphics/G.png
qucat/.graphics/G_hover.jpg
qucat/.graphics/G_hover.png
qucat/.graphics/G_hover_selected.jpg
qucat/.graphics/G_hover_selected.png
qucat/.graphics/G_selected.jpg
qucat/.graphics/G_selected.png
qucat/.graphics/J.jpg
qucat/.graphics/J.png
qucat/.graphics/J_hover.jpg
qucat/.graphics/J_hover.png
qucat/.graphics/J_hover_selected.jpg
qucat/.graphics/J_hover_selected.png
qucat/.graphics/J_selected.jpg
qucat/.graphics/J_selected.png
qucat/.graphics/L.jpg
qucat/.graphics/L.png
qucat/.graphics/L_hover.jpg
qucat/.graphics/L_hover.png
qucat/.graphics/L_hover_selected.jpg
qucat/.graphics/L_hover_selected.png
qucat/.graphics/L_selected.jpg
qucat/.graphics/L_selected.png
qucat/.graphics/R.jpg
qucat/.graphics/R.png
qucat/.graphics/R_hover.jpg
qucat/.graphics/R_hover.png
qucat/.graphics/R_hover_selected.jpg
qucat/.graphics/R_hover_selected.png
qucat/.graphics/R_selected.jpg
qucat/.graphics/R_selected.png
qucat-1.0.3.dist-info/LICENSE
qucat-1.0.3.dist-info/METADATA
qucat-1.0.3.dist-info/WHEEL
qucat-1.0.3.dist-info/top_level.txt
qucat-1.0.3.dist-info/RECORD
