Metadata-Version: 2.1
Name: qucat
Version: 1.0.3
Summary: QUantum Circuit Analysis Tool
Home-page: https://qucat.org
Author: Mario Gely
Author-email: mario.f.gely@gmail.com
License: UNKNOWN
Platform: UNKNOWN
Classifier: Programming Language :: Python :: 3
Classifier: License :: OSI Approved :: MIT License
Classifier: Operating System :: OS Independent
Requires-Python: >3.0.0
Requires-Dist: numpy
Requires-Dist: scipy
Requires-Dist: matplotlib
Requires-Dist: sympy (>=1.8)
Requires-Dist: pillow
